LICENSE
README.md
setup.py
pychop/__init__.py
pychop/demo_harmonic.py
pychop/float_params.py
pychop/simulate.py
pychop/test_chop.py
pychop.egg-info/PKG-INFO
pychop.egg-info/SOURCES.txt
pychop.egg-info/dependency_links.txt
pychop.egg-info/requires.txt
pychop.egg-info/top_level.txt
pychop/numpy/__init__.py
pychop/numpy/chop.py
pychop/numpy/roundit.py
pychop/torch/__init__.py
pychop/torch/chop.py
pychop/torch/layers.py
pychop/torch/quant.py
pychop/torch/roundit.py