Metadata-Version: 2.1
Name: pychop
Version: 0.1.7
Summary: Python code for simulating low precision floating-point arithmetic
Home-page: https://github.com/chenxinye/pychop.git
Author: Xinye Chen
Author-email: xinyechenai@gmail.com
Maintainer: Xinye Chen
Maintainer-email: xinyechenai@gmail.com
License: MIT License
Platform: UNKNOWN
Classifier: Intended Audience :: Science/Research
Classifier: Intended Audience :: Developers
Classifier: Programming Language :: Python
Classifier: Topic :: Software Development
Classifier: Topic :: Scientific/Engineering
Classifier: Operating System :: Microsoft :: Windows
Classifier: Operating System :: Unix
Classifier: Programming Language :: Python :: 3
License-File: LICENSE
